rnamoip/__init__.py
rnamoip/add_interactions_results.py
rnamoip/batch_execute.py
rnamoip/compare_tools.py
rnamoip/config.py
rnamoip/execute_pdb.py
rnamoip/graph_generator.py
rnamoip/logger.py
rnamoip/main.py
rnamoip/multi_batch_analysis.py
rnamoip/parse_raw_pdbs.py
rnamoip/predicter.py
rnamoip/renderer.py
rnamoip/rin_v2.py
rnamoip/analysis/__init__.py
rnamoip/analysis/analysis_result.py
rnamoip/analysis/comparer.py
rnamoip/analysis/comparer_result.py
rnamoip/analysis/pdb_interaction.py
rnamoip/analysis/rin_interaction.py
rnamoip/analysis/model/__init__.py
rnamoip/analysis/model/chain.py
rnamoip/analysis/model/interaction.py
rnamoip/analysis/model/pdb.py
rnamoip/data/configuration.json
rnamoip/data/rins.json
rnamoip/database/__init__.py
rnamoip/database/catalog.py
rnamoip/database/model/__init__.py
rnamoip/database/model/common.py
rnamoip/database/model/motif.py
rnamoip/database/model/strand.py
rnamoip/helpers/__init__.py
rnamoip/helpers/base_pairing.py
rnamoip/helpers/sequence.py
rnamoip/helpers/structure.py
rnamoip/helpers/validation.py
rnamoip/helpers/parser/config.py
rnamoip/helpers/parser/desc.py
rnamoip/helpers/parser/raw_pdbs_json.py
rnamoip/helpers/parser/rin.py
rnamoip/ip_model/__init__.py
rnamoip/ip_model/ip_manager.py
rnamoip/ip_model/model/base_model.py
rnamoip/ip_model/model/cplex_model.py
rnamoip/ip_model/model/glpk_model.py
rnamoip/ip_model/model/google_model.py
rnamoip/ip_model/model/gurobi_model.py
rnamoip/ip_model/model/mip_model.py
rnamoip/ip_model/module/__init__.py
rnamoip/ip_model/module/common.py
rnamoip/ip_model/module/ipknot.py
rnamoip/ip_model/module/rnamoip.py
rnamoip/scripts/__init__.py
rnamoip/scripts/_rin_utils.py
rnamoip/scripts/_scripts.md
rnamoip/scripts/chains_to_fasta.py
rnamoip/scripts/chains_to_stockholm.py
rnamoip/scripts/combine_json.py
rnamoip/scripts/diff_with_inital_ss.py
rnamoip/scripts/extract_alignement_list.py
rnamoip/scripts/filter_spotrna_chains.py
rnamoip/scripts/find_best_solution.py
rnamoip/scripts/forgi_graph.py
rnamoip-1.1.2.dist-info/METADATA
rnamoip-1.1.2.dist-info/WHEEL
rnamoip-1.1.2.dist-info/licenses/LICENSE
rnamoip-1.1.2.dist-info/RECORD
