Metadata-Version: 2.1
Name: rnamoip
Version: 1.1.2
Summary: RNAMoIP: Integer Programing Framework to predict RNA secondary structure
Project-URL: Homepage, https://rnamoip.cbe.uqam.ca
Project-URL: Source, https://gitlab.info.uqam.ca/cbe/RNAMoIP
Author-email: Gabriel Loyer <loyer.gab@gmail.com>, Vladimir Reinharz <vreinharz@protonmail.com>
License-File: LICENSE
Classifier: License :: OSI Approved :: MIT License
Classifier: Operating System :: OS Independent
Classifier: Programming Language :: Python :: 3
Classifier: Programming Language :: Python :: 3.9
Classifier: Programming Language :: Python :: 3.10
Classifier: Programming Language :: Python :: 3.11
Requires-Python: <3.12,>=3.9
Requires-Dist: colorama==0.4.6
Requires-Dist: mip==1.15.0
Requires-Dist: ortools==9.6.2534
Requires-Dist: viennarna==2.6.4
Provides-Extra: gurobi
Requires-Dist: gurobipy==11.0.0; python_version < '3.11' and extra == 'gurobi'
